colemen_mint_setup/ColemenMintSetup.py
colemen_mint_setup/__init__.py
colemen_mint_setup/aliasSettings.py
colemen_mint_setup/appSettings.py
colemen_mint_setup/hotkeySettings.py
colemen_mint_setup/themeSettings.py
colemen_mint_setup/utils.py
colemen_mint_setup/settings/__init__.py
colemen_mint_setup/settings/control.py
colemen_mint_setup/settings/types.py
colemen_mint_setup-0.0.2.dist-info/METADATA
colemen_mint_setup-0.0.2.dist-info/WHEEL
colemen_mint_setup-0.0.2.dist-info/top_level.txt
colemen_mint_setup-0.0.2.dist-info/RECORD
